[
  {
    "ContainingType": "DistrubutedCache.Controllers.ValuesController",
    "Method": "Get",
    "RelativePath": "api/Values/get",
    "HttpMethod": "GET",
    "IsController": true,
    "Order": 0,
    "Parameters": [],
    "ReturnTypes": []
  },
  {
    "ContainingType": "DistrubutedCache.Controllers.ValuesController",
    "Method": "Set",
    "RelativePath": "api/Values/set",
    "HttpMethod": "GET",
    "IsController": true,
    "Order": 0,
    "Parameters": [
      {
        "Name": "name",
        "Type": "System.String",
        "IsRequired": false
      },
      {
        "Name": "surname",
        "Type": "System.String",
        "IsRequired": false
      }
    ],
    "ReturnTypes": []
  }
]